doup/EntryPoint.py
doup/__init__.py
doup/analyzer/ImageNameAnalyzer.py
doup/analyzer/StringAnalyzer.py
doup/analyzer/TagAnalyzer.py
doup/crawler/DirectoryCrawler.py
doup/crawler/DockerhubCrawler.py
doup/dto/DirectorySummary.py
doup/dto/DockerImage.py
doup/services/FileService.py
doup/services/OutputService.py
doup-4.0.1.dist-info/LICENSE
doup-4.0.1.dist-info/METADATA
doup-4.0.1.dist-info/WHEEL
doup-4.0.1.dist-info/entry_points.txt
doup-4.0.1.dist-info/top_level.txt
doup-4.0.1.dist-info/RECORD
