Metadata-Version: 2.1
Name: doup
Version: 4.0.1
Summary: doup is a command line tool to find and update Docker-Image-Strings in project files.
Author-email: Kay Gerlitzki <developed@kygr.org>
Project-URL: Homepage, https://gitlab.com/doup1/doup
Project-URL: Bug Tracker, https://gitlab.com/doup1/doup/-/issues
Classifier: Programming Language :: Python :: 3
Classifier: License :: OSI Approved :: MIT License
Classifier: Operating System :: OS Independent
License-File: LICENSE
Requires-Dist: termcolor
Requires-Dist: requests
Requires-Dist: tabulate
Requires-Dist: types-tabulate
